poetry_plugin_code_artifact/__init__.py
poetry_plugin_code_artifact/plugin.py
poetry_plugin_code_artifact-1.0.0.dist-info/LICENSE
poetry_plugin_code_artifact-1.0.0.dist-info/METADATA
poetry_plugin_code_artifact-1.0.0.dist-info/WHEEL
poetry_plugin_code_artifact-1.0.0.dist-info/entry_points.txt
poetry_plugin_code_artifact-1.0.0.dist-info/RECORD
