Metadata-Version: 2.1
Name: poetry-plugin-code-artifact
Version: 1.0.0
Summary: Plugin for poetry that simplifies using AWS CodeArtifact for publishing and downloading dependencies..
Home-page: https://github.com/bellis/poetry-plugin-code-artifact
License: MIT
Author: Ben Ellis
Author-email: ben.ellis@softweyr.co.uk
Requires-Python: >=3.7,<4.0
Classifier: Development Status :: 3 - Alpha
Classifier: Intended Audience :: Developers
Classifier: Intended Audience :: Information Technology
Classifier: Intended Audience :: System Administrators
Classifier: License :: OSI Approved :: MIT License
Classifier: Operating System :: OS Independent
Classifier: Programming Language :: Python
Classifier: Programming Language :: Python :: 3
Classifier: Programming Language :: Python :: 3.7
Classifier: Programming Language :: Python :: 3.8
Classifier: Programming Language :: Python :: 3.9
Classifier: Programming Language :: Python :: 3.10
Classifier: Programming Language :: Python :: 3.11
Classifier: Programming Language :: Python :: 3.12
Classifier: Programming Language :: Python :: 3 :: Only
Classifier: Topic :: Software Development
Classifier: Topic :: Software Development :: Libraries
Classifier: Topic :: Software Development :: Libraries :: Application Frameworks
Classifier: Topic :: Software Development :: Libraries :: Python Modules
Classifier: Topic :: Software Development :: Version Control :: Git
Classifier: Topic :: System :: Archiving :: Packaging
Classifier: Topic :: System :: Installation/Setup
Classifier: Topic :: System :: Software Distribution
Requires-Dist: boto3 (>=1.27.0,<2.0.0)
Requires-Dist: poetry (>=1.2,<2.0)
Requires-Dist: pyopenssl (>=23.2.0,<24.0.0)
Project-URL: Documentation, https://github.com/bellis/poetry-plugin-code-artifact
